nimutool/__init__.py
nimutool/nimucsv.py
nimutool/nimucsvplot.py
nimutool/nimudebug.py
nimutool/canbus/__init__.py
nimutool/canbus/bus_block_reader.py
nimutool/canbus/bus_reader.py
nimutool/canbus/bus_synchronizer.py
nimutool/canbus/can_message.py
nimutool/data/__init__.py
nimutool/data/conversion.py
nimutool/data/plotter.py
nimutool/data/reader.py
nimutool/data/writer.py
nimutool/parser/__init__.py
nimutool/parser/common/__init__.py
nimutool/parser/common/can_parser.py
nimutool/parser/common/datatype_parsers.py
nimutool/parser/public/__init__.py
nimutool/parser/public/nordic_inertial_parser.py
nimutool/parser/public/pacific_inertial_parser.py
nimutool-0.1.12.dist-info/METADATA
nimutool-0.1.12.dist-info/WHEEL
nimutool-0.1.12.dist-info/top_level.txt
nimutool-0.1.12.dist-info/RECORD
